poetry_build_testing_12345/__init__.py
awesome_mprox-0.1.9.dist-info/WHEEL
awesome_mprox-0.1.9.dist-info/METADATA
awesome_mprox-0.1.9.dist-info/RECORD
