Metadata-Version: 2.1
Name: awesome-mprox
Version: 0.1.9
Summary: 
Author: Your Name
Author-email: you@example.com
Requires-Python: >=3.9,<4.0
Classifier: Programming Language :: Python :: 3
Classifier: Programming Language :: Python :: 3.9
Classifier: Programming Language :: Python :: 3.10
Classifier: Programming Language :: Python :: 3.11
Provides-Extra: databases
Requires-Dist: boto3; extra == "databases"
Requires-Dist: requests
